[
  {
    "agent": "assistant",
    "action_type": "extract",
    "state": "Collecting information to identify the book title based on given criteria.",
    "original_index": 0
  },
  {
    "agent": "user",
    "action_type": "search",
    "state": "Gathering information about books by James Beard Award winners for Frontier Restaurant.",
    "original_index": 1
  },
  {
    "agent": "user",
    "action_type": "search",
    "state": "Retrieved search results for James Beard Award nominees in New Mexico.",
    "original_index": 2
  },
  {
    "agent": "assistant",
    "action_type": "search",
    "state": "Refining search for books recommending the Frontier Restaurant by James Beard Award winners.",
    "original_index": 3
  },
  {
    "agent": "user",
    "action_type": "search",
    "state": "Retrieved search results for James Beard Award nominees in New Mexico.",
    "original_index": 4
  },
  {
    "agent": "user",
    "action_type": "search",
    "state": "Identifying James Beard Award winners related to New Mexican cuisine.",
    "original_index": 5
  },
  {
    "agent": "user",
    "action_type": "search",
    "state": "Retrieved search results for New Mexico chefs and restaurants nominated for James Beard Awards.",
    "original_index": 6
  },
  {
    "agent": "assistant",
    "action_type": "search",
    "state": "Looking for books by Cheryl Jamison mentioning Frontier Restaurant.",
    "original_index": 7
  },
  {
    "agent": "user",
    "action_type": "search",
    "state": "Retrieved multiple search results about Cheryl Alters Jamison and her cookbooks.",
    "original_index": 8
  },
  {
    "agent": "user",
    "action_type": "search",
    "state": "Gathering information about the book to verify restaurant recommendations.",
    "original_index": 9
  }
]