[
  {
    "agent": "assistant",
    "action_type": "collect",
    "state": "Gathering information to determine the number of images in the Lego Wikipedia article.",
    "original_index": 0
  },
  {
    "agent": "assistant",
    "action_type": "extract",
    "state": "Extracting content from the Lego Wikipedia article including images and tables.",
    "original_index": 1
  },
  {
    "agent": "user",
    "action_type": "confirm",
    "state": "execution succeeded with no output",
    "original_index": 2
  },
  {
    "agent": "assistant",
    "action_type": "write_script",
    "state": "Creating a script to count image tags in a Wikipedia article",
    "original_index": 3
  },
  {
    "agent": "user",
    "action_type": "report",
    "state": "execution succeeded with 28 images found in the article",
    "original_index": 4
  },
  {
    "agent": "user",
    "action_type": "verify",
    "state": "Confirmed the image count from extraction is 28 and ready to terminate.",
    "original_index": 5
  },
  {
    "agent": "user",
    "action_type": "agree",
    "state": "User confirms the verification of 28 extracted images.",
    "original_index": 6
  },
  {
    "agent": "assistant",
    "action_type": "terminate",
    "state": "Session is being concluded after verification agreement.",
    "original_index": 7
  },
  {
    "agent": "user",
    "action_type": "inform",
    "state": "User indicates no code to execute and suggests conversation management rules.",
    "original_index": 8
  },
  {
    "agent": "user",
    "action_type": "terminate",
    "state": "User is ending the current task or session.",
    "original_index": 9
  }
]