[
  {
    "agent": "human",
    "action_type": "ask",
    "state": "inquire about fish bag volume from a specific paper",
    "original_index": 0
  },
  {
    "agent": "Orchestrator (thought)",
    "action_type": "plan",
    "state": "Outline steps to gather information about the fish bag's volume from a research paper.",
    "original_index": 1
  },
  {
    "agent": "Orchestrator (thought)",
    "action_type": "inform",
    "state": "Instructing to search for specific paper to extract information.",
    "original_index": 2
  },
  {
    "agent": "Orchestrator (-> WebSurfer)",
    "action_type": "search",
    "state": "Locate specific volume of fish bag in cubic meters from paper.",
    "original_index": 3
  },
  {
    "agent": "WebSurfer",
    "action_type": "type",
    "state": "Entered search query for a specific academic paper",
    "original_index": 4
  },
  {
    "agent": "Orchestrator (thought)",
    "action_type": "inform",
    "state": "Instructing WebSurfer to locate specific information in a journal article.",
    "original_index": 5
  },
  {
    "agent": "Orchestrator (-> WebSurfer)",
    "action_type": "navigate",
    "state": "Locate specific volume of fish bag in journal article",
    "original_index": 6
  },
  {
    "agent": "Orchestrator (thought)",
    "action_type": "inform",
    "state": "Indicating the next speaker in the sequence.",
    "original_index": 7
  },
  {
    "agent": "WebSurfer",
    "action_type": "click",
    "state": "Accessed a journal article about dragon diet feasibility.",
    "original_index": 8
  },
  {
    "agent": "Orchestrator (thought)",
    "action_type": "update",
    "state": "Updated the ledger with current task status and next steps.",
    "original_index": 9
  },
  {
    "agent": "Orchestrator (-> WebSurfer)",
    "action_type": "download",
    "state": "Download the paper PDF and search for fish bag volume.",
    "original_index": 10
  },
  {
    "agent": "Orchestrator (thought)",
    "action_type": "inform",
    "state": "Indicating the next speaker in the sequence.",
    "original_index": 11
  },
  {
    "agent": "WebSurfer",
    "action_type": "click",
    "state": "User clicked on the PDF link for the article.",
    "original_index": 12
  },
  {
    "agent": "Orchestrator (thought)",
    "action_type": "inform",
    "state": "Instructing WebSurfer to examine the PDF for specific volume information.",
    "original_index": 13
  },
  {
    "agent": "Orchestrator (-> WebSurfer)",
    "action_type": "extract",
    "state": "Find the volume of the fish bag in cubic meters from the PDF.",
    "original_index": 14
  },
  {
    "agent": "Orchestrator (thought)",
    "action_type": "inform",
    "state": "Indicating the next speaker in the sequence.",
    "original_index": 15
  },
  {
    "agent": "WebSurfer",
    "action_type": "type",
    "state": "Entered search query into article details section",
    "original_index": 16
  },
  {
    "agent": "Orchestrator (thought)",
    "action_type": "inform",
    "state": "Requesting FileSurfer to check PDF for fish bag volume information.",
    "original_index": 17
  },
  {
    "agent": "Orchestrator (-> FileSurfer)",
    "action_type": "request",
    "state": "Check PDF for fish bag volume information",
    "original_index": 18
  },
  {
    "agent": "Orchestrator (thought)",
    "action_type": "inform",
    "state": "Notified about model mismatch for FileSurfer agent.",
    "original_index": 19
  },
  {
    "agent": "FileSurfer",
    "action_type": "report",
    "state": "File not found error for the specified PDF document.",
    "original_index": 20
  },
  {
    "agent": "Orchestrator (thought)",
    "action_type": "inform",
    "state": "Requesting a search for an accessible PDF of a specific paper.",
    "original_index": 21
  },
  {
    "agent": "Orchestrator (-> WebSurfer)",
    "action_type": "search",
    "state": "Find an alternative link for the PDF and ensure successful download.",
    "original_index": 22
  },
  {
    "agent": "Orchestrator (thought)",
    "action_type": "inform",
    "state": "Indicating the next speaker in the sequence.",
    "original_index": 23
  },
  {
    "agent": "WebSurfer",
    "action_type": "click",
    "state": "User clicked on a PDF link to access the document.",
    "original_index": 24
  },
  {
    "agent": "Orchestrator (thought)",
    "action_type": "inform",
    "state": "Requesting alternative sources for a specific PDF document.",
    "original_index": 25
  },
  {
    "agent": "Orchestrator (-> WebSurfer)",
    "action_type": "search",
    "state": "Locate accessible PDF of the University of Leicester paper.",
    "original_index": 26
  },
  {
    "agent": "Orchestrator (thought)",
    "action_type": "inform",
    "state": "Indicating the next speaker in the sequence.",
    "original_index": 27
  },
  {
    "agent": "WebSurfer",
    "action_type": "click",
    "state": "Initiated download of a PDF file successfully.",
    "original_index": 28
  },
  {
    "agent": "Orchestrator (thought)",
    "action_type": "inform",
    "state": "Instructing FileSurfer to open a PDF for specific information retrieval.",
    "original_index": 29
  },
  {
    "agent": "Orchestrator (thought)",
    "action_type": "replan",
    "state": "Addressing model mismatch and adjusting execution plan.",
    "original_index": 30
  },
  {
    "agent": "Orchestrator (thought)",
    "action_type": "plan",
    "state": "Developing a strategy to address a user request regarding a specific volume calculation.",
    "original_index": 31
  },
  {
    "agent": "Orchestrator (thought)",
    "action_type": "inform",
    "state": "Providing instructions to verify and extract information from a PDF file.",
    "original_index": 32
  },
  {
    "agent": "Orchestrator (-> FileSurfer)",
    "action_type": "verify",
    "state": "Check if the PDF download is complete and extract relevant keywords.",
    "original_index": 33
  },
  {
    "agent": "Orchestrator (thought)",
    "action_type": "inform",
    "state": "indicating the next speaker in the sequence",
    "original_index": 34
  },
  {
    "agent": "FileSurfer",
    "action_type": "report",
    "state": "File not found error for the specified PDF document.",
    "original_index": 35
  },
  {
    "agent": "Orchestrator (thought)",
    "action_type": "update",
    "state": "Reviewed access issues and instructed to redownload a specific paper.",
    "original_index": 36
  },
  {
    "agent": "Orchestrator (-> WebSurfer)",
    "action_type": "download",
    "state": "redownload the specified paper and provide file path",
    "original_index": 37
  },
  {
    "agent": "Orchestrator (thought)",
    "action_type": "inform",
    "state": "Indicating the next speaker in the sequence.",
    "original_index": 38
  },
  {
    "agent": "WebSurfer",
    "action_type": "type",
    "state": "Entered search query into the search bar",
    "original_index": 39
  },
  {
    "agent": "Orchestrator (thought)",
    "action_type": "inform",
    "state": "Instructing WebSurfer to download the correct PDF file for necessary information.",
    "original_index": 40
  },
  {
    "agent": "Orchestrator (-> WebSurfer)",
    "action_type": "click",
    "state": "Access and download a specific PDF from a journal page.",
    "original_index": 41
  },
  {
    "agent": "Orchestrator (thought)",
    "action_type": "inform",
    "state": "Indicating the next speaker in the sequence.",
    "original_index": 42
  },
  {
    "agent": "WebSurfer",
    "action_type": "click",
    "state": "Accessed a journal article about dragon diet feasibility.",
    "original_index": 43
  },
  {
    "agent": "Orchestrator (thought)",
    "action_type": "inform",
    "state": "Instructing to download a PDF for extracting fish bag volume.",
    "original_index": 44
  },
  {
    "agent": "Orchestrator (-> WebSurfer)",
    "action_type": "click",
    "state": "Initiate download of a specific PDF document from a journal page.",
    "original_index": 45
  },
  {
    "agent": "Orchestrator (thought)",
    "action_type": "inform",
    "state": "Indicating the next speaker in the sequence.",
    "original_index": 46
  },
  {
    "agent": "WebSurfer",
    "action_type": "click",
    "state": "User clicked on a PDF link to access the document.",
    "original_index": 47
  },
  {
    "agent": "Orchestrator (thought)",
    "action_type": "update",
    "state": "Evaluating progress and next steps for data extraction from a PDF.",
    "original_index": 48
  },
  {
    "agent": "Orchestrator (-> FileSurfer)",
    "action_type": "search",
    "state": "Extract and summarize information from a PDF based on specific keywords.",
    "original_index": 49
  },
  {
    "agent": "Orchestrator (thought)",
    "action_type": "report",
    "state": "Error occurred while processing a publish message for the next speaker.",
    "original_index": 50
  }
]